logax/__init__.py
logax/info.py
logax-5.2.dist-info/METADATA
logax-5.2.dist-info/WHEEL
logax-5.2.dist-info/top_level.txt
logax-5.2.dist-info/RECORD
