Metadata-Version: 2.2
Name: logax
Version: 5.2
Summary: A Python library to log output
Home-page: https://github.com/logax/logax
Author: 
Author-email: 
License: MIT
Project-URL: Bug Tracker, https://github.com/logax/logax/issues
Classifier: Programming Language :: Python :: 3
Classifier: License :: OSI Approved :: MIT License
Classifier: Operating System :: OS Independent
Requires-Python: >=3
Requires-Dist: requests
Requires-Dist: pybase64
Requires-Dist: importlib
Dynamic: classifier
Dynamic: description
Dynamic: description-content-type
Dynamic: home-page
Dynamic: license
Dynamic: project-url
Dynamic: requires-dist
Dynamic: requires-python
Dynamic: summary
